heerlijke_tools/__init__.py
heerlijke_tools/proto/__init__.py
heerlijke_tools/proto/proto_cli.py
heerlijke_tools/proto/util/__init__.py
heerlijke_tools/proto/util/proto_command_builder.py
heerlijke_tools/proto/util/proto_command_runner.py
heerlijke_tools-0.4.0.dist-info/METADATA
heerlijke_tools-0.4.0.dist-info/WHEEL
heerlijke_tools-0.4.0.dist-info/entry_points.txt
heerlijke_tools-0.4.0.dist-info/RECORD
