Metadata-Version: 2.1
Name: heerlijke-tools
Version: 0.4.0
Summary: Toolbox of development utilities for my personal use.
Project-URL: Documentation, https://cringelord-heerlijkeheer-806eb581859167e3efa6c9df4ab5e4bf17987f.gitlab.io/
Project-URL: Repository, https://gitlab.com/HeerlijkeHeer/HeerlijkeTools
Author-email: Thomas Vanhelden <thomas.vanhelden@gmail.com>
License: # Heerlijke-Tools End-User License Agreement (EULA)
Requires-Python: >=3.12
Requires-Dist: click>=8.1.7
Requires-Dist: grpcio-tools>=1.60.1
Requires-Dist: protoletariat>=3.2.19
